.travis.yml
CHANGELOG.rst
LICENSE.txt
MANIFEST.in
README.rst
docker-compose.yml
install.py
requirements-dev.txt
requirements.txt
setup.py
Telemeta.egg-info/PKG-INFO
Telemeta.egg-info/SOURCES.txt
Telemeta.egg-info/dependency_links.txt
Telemeta.egg-info/not-zip-safe
Telemeta.egg-info/requires.txt
Telemeta.egg-info/top_level.txt
app/.init
app/__init__.py
app/manage.py
app/robots.txt
app/settings.py
app/settings.pyc
app/urls.py
app/worker.py
app/wsgi.py
app/enumeration/enumeration.txt
app/fixtures/original_format.txt
app/scripts/app.sh
app/scripts/diag.sh
app/scripts/enumeration.sh
app/scripts/install_plugins.sh
app/scripts/modelviz.py
app/scripts/setup_plugins.sh
app/scripts/update_schema.sh
app/scripts/wait.sh
app/scripts/worker.sh
env/debug.env
env/debug.yml
env/dev.yml
env/prod.env
scripts/kdenlive/__init__.py
scripts/kdenlive/auto_fade.py
scripts/kdenlive/auto_fade_batch.py
scripts/kdenlive/fade.py
scripts/kdenlive/mlt_fix_threads.sh
scripts/kdenlive/mlt_process_batch.py
scripts/old/crem_checker.py
scripts/old/process-waveform-cgi.py
scripts/old/telemeta-backup.py
scripts/old/telemeta-crem-import-alt_ids.py
scripts/old/telemeta-crem-import-test.py
scripts/old/telemeta-crem-import.py
scripts/old/telemeta-media-link.py
scripts/sql/backup_db.sh
scripts/sql/convert_myisam_to_innodb.sql
scripts/sql/drop_timeside.sql
scripts/sql/import_sql.sh
scripts/sql/restore_db.sh
scripts/transcode/create_thumbs.py
scripts/transcode/remux_fix_media.py
scripts/transcode/transcode.py
telemeta/__init__.py
telemeta/admin.py
telemeta/apps.py
telemeta/cache.py
telemeta/config.py
telemeta/context_processors.py
telemeta/core.py
telemeta/search_indexes.py
telemeta/tasks.py
telemeta/url2.py
telemeta/urls.py
telemeta/backup/__init__.py
telemeta/backup/core.py
telemeta/forms/__init__.py
telemeta/forms/boolean_form.py
telemeta/forms/format.py
telemeta/forms/haystack_form.py
telemeta/forms/language.py
telemeta/forms/media.py
telemeta/forms/system.py
telemeta/interop/__init__.py
telemeta/interop/oai.py
telemeta/interop/oaidatasource.py
telemeta/interop/oaitest.py
telemeta/locale/.git
telemeta/locale/LICENSE
telemeta/locale/README.md
telemeta/locale/ar_TN/LC_MESSAGES/django.mo
